ezq/__init__.py
ezq/py.typed
ezq-3.0.4.dist-info/LICENSE.md
ezq-3.0.4.dist-info/METADATA
ezq-3.0.4.dist-info/WHEEL
ezq-3.0.4.dist-info/top_level.txt
ezq-3.0.4.dist-info/RECORD
