Metadata-Version: 2.1
Name: ezq
Version: 3.0.4
Summary: Simple wrapper for python multiprocessing and threading.
Author-email: Metaist LLC <metaist@metaist.com>
License: MIT
Project-URL: Homepage, https://github.com/metaist/ezq
Project-URL: Documentation, https://metaist.github.io/ezq/
Project-URL: Repository, https://github.com/metaist/ezq.git
Project-URL: Changelog, https://github.com/metaist/ezq/blob/main/CHANGELOG.md
Keywords: queue,worker,multiprocessing,threading
Classifier: Development Status :: 4 - Beta
Classifier: Intended Audience :: Developers
Classifier: License :: OSI Approved :: MIT License
Classifier: Natural Language :: English
Classifier: Operating System :: OS Independent
Classifier: Programming Language :: Python
Classifier: Programming Language :: Python :: 3
Classifier: Programming Language :: Python :: 3 :: Only
Classifier: Programming Language :: Python :: 3.8
Classifier: Programming Language :: Python :: 3.9
Classifier: Programming Language :: Python :: 3.10
Classifier: Programming Language :: Python :: 3.11
Classifier: Topic :: Software Development :: Libraries
Classifier: Typing :: Typed
Requires-Python: >=3.8
License-File: LICENSE.md
Requires-Dist: multiprocess (~=0.70.14)
Provides-Extra: dev
Requires-Dist: black ; extra == 'dev'
Requires-Dist: coverage ; extra == 'dev'
Requires-Dist: mypy ; extra == 'dev'
Requires-Dist: pdoc3 ; extra == 'dev'
Requires-Dist: pytest ; extra == 'dev'
Requires-Dist: pytest-cov ; extra == 'dev'
Requires-Dist: ruff ; extra == 'dev'
